wds_client/__init__.py
wds_client/api_client.py
wds_client/api_response.py
wds_client/configuration.py
wds_client/exceptions.py
wds_client/py.typed
wds_client/rest.py
wds_client/api/__init__.py
wds_client/api/capabilities_api.py
wds_client/api/collection_api.py
wds_client/api/general_wds_information_api.py
wds_client/api/import_api.py
wds_client/api/job_api.py
wds_client/api/record_api.py
wds_client/api/records_api.py
wds_client/api/schema_api.py
wds_client/api/workspace_api.py
wds_client/models/__init__.py
wds_client/models/app.py
wds_client/models/attribute_data_type.py
wds_client/models/attribute_schema.py
wds_client/models/attribute_schema_update.py
wds_client/models/batch_operation.py
wds_client/models/batch_record_request.py
wds_client/models/batch_response.py
wds_client/models/build.py
wds_client/models/capabilities.py
wds_client/models/collection.py
wds_client/models/collection_request.py
wds_client/models/commit.py
wds_client/models/delete_records_request.py
wds_client/models/delete_records_response.py
wds_client/models/error_response.py
wds_client/models/generic_job.py
wds_client/models/git.py
wds_client/models/import_request.py
wds_client/models/job_v1.py
wds_client/models/record_query_response.py
wds_client/models/record_request.py
wds_client/models/record_response.py
wds_client/models/record_type_schema.py
wds_client/models/search_filter.py
wds_client/models/search_request.py
wds_client/models/search_sort_direction.py
wds_client/models/status_response.py
wds_client/models/tsv_upload_response.py
wds_client/models/version_response.py
wds_client/models/workspace_init.py
wds_client/models/workspace_init_clone.py
wds_client-0.38.37.dist-info/METADATA
wds_client-0.38.37.dist-info/WHEEL
wds_client-0.38.37.dist-info/top_level.txt
wds_client-0.38.37.dist-info/RECORD
