Metadata-Version: 2.1
Name: wds-client
Version: 0.38.37
Summary: Workspace Data Service
Home-page: 
Author: OpenAPI Generator community
Author-email: team@openapitools.org
License: BSD
Keywords: OpenAPI,OpenAPI-Generator,Workspace Data Service
Requires-Dist: urllib3 <2.1.0,>=1.25.3
Requires-Dist: python-dateutil
Requires-Dist: pydantic >=2
Requires-Dist: typing-extensions >=4.7.1
